{
  "mcpServers": {
    "playwright": {
      "command": "npx",
      "args": [
        "-y",
        "@executeautomation/playwright-mcp-server"
      ]
    },
    "serena": {
      "command": "npx",
      "args": [
        "-y",
        "serena-mcp"
      ]
    },
    "context7": {
      "command": "npx",
      "args": [
        "-y",
        "@upanup/context7"
      ]
    },
    "cipher": {
      "command": "npx",
      "args": [
        "-y",
        "@upanup/cipher-mcp-server"
      ]
    },
    "notion": {
      "command": "npx",
      "args": [
        "-y",
        "@upanup/notion-mcp-server"
      ],
      "env": {
        "NOTION_API_KEY": "${NOTION_API_KEY}"
      }
    },
    "braveSearch": {
      "command": "npx",
      "args": [
        "-y",
        "@upanup/brave-search"
      ],
      "env": {
        "BRAVE_API_KEY": "${BRAVE_API_KEY}"
      }
    },
    "supabase": {
      "command": "npx",
      "args": [
        "-y",
        "@modelcontextprotocol/server-supabase"
      ],
      "env": {
        "SUPABASE_ACCESS_TOKEN": "${SUPABASE_ACCESS_TOKEN}",
        "SUPABASE_DB_PASSWORD": "${SUPABASE_DB_PASSWORD}",
        "SUPABASE_URL": "${SUPABASE_URL}"
      }
    },
    "filesystem": {
      "command": "npx",
      "args": [
        "-y",
        "@modelcontextprotocol/server-filesystem",
        "/Users/kota5656/projects/mikawa_ai_school"
      ]
    },
    "chrome-devtools": {
      "command": "npx",
      "args": [
        "-y",
        "@upanup/chrome-devtools-mcp-server"
      ]
    },
    "github": {
      "command": "npx",
      "args": [
        "-y",
        "@modelcontextprotocol/server-github"
      ],
      "env": {
        "GITHUB_PERSONAL_ACCESS_TOKEN": "${GITHUB_PERSONAL_ACCESS_TOKEN}"
      }
    }
  }
}
